README.rst
setup.py
codename/__init__.py
codename/codename.py
codename.egg-info/PKG-INFO
codename.egg-info/SOURCES.txt
codename.egg-info/dependency_links.txt
codename.egg-info/entry_points.txt
codename.egg-info/top_level.txt