Metadata-Version: 1.1
Name: codename
Version: 1.0
Summary: Codename generator. Credits to "projectcodename.com".
Home-page: https://github.com/and3rson/codename
Author: Andrew Dunai
Author-email: a@dun.ai
License: UNKNOWN
Keywords: python project codename generator code name
Platform: UNKNOWN
Classifier: Development Status :: 5 - Production/Stable
Classifier: Intended Audience :: Developers
Classifier: Programming Language :: Python :: 2.7
Classifier: Programming Language :: Python :: 3.6
